dj_apis_allauth/__init__.py
dj_apis_allauth/__version__.py
dj_apis_allauth/admin.py
dj_apis_allauth/app_settings.py
dj_apis_allauth/apps.py
dj_apis_allauth/forms.py
dj_apis_allauth/jwt_auth.py
dj_apis_allauth/migrations/__init__.py
dj_apis_allauth/models.py
dj_apis_allauth/registration/__init__.py
dj_apis_allauth/registration/serializers.py
dj_apis_allauth/registration/urls.py
dj_apis_allauth/registration/views.py
dj_apis_allauth/serializers.py
dj_apis_allauth/social_serializers.py
dj_apis_allauth/tests/__init__.py
dj_apis_allauth/tests/django_urls.py
dj_apis_allauth/tests/mixins.py
dj_apis_allauth/tests/requirements.txt
dj_apis_allauth/tests/settings.py
dj_apis_allauth/tests/test_api.py
dj_apis_allauth/tests/test_serializers.py
dj_apis_allauth/tests/test_social.py
dj_apis_allauth/tests/test_utils.py
dj_apis_allauth/tests/urls.py
dj_apis_allauth/tests/utils.py
dj_apis_allauth/tests.py
dj_apis_allauth/urls.py
dj_apis_allauth/utils.py
dj_apis_allauth/views.py
dj_apis_allauth-1.0.0.dist-info/METADATA
dj_apis_allauth-1.0.0.dist-info/WHEEL
dj_apis_allauth-1.0.0.dist-info/licenses/LICENSE
dj_apis_allauth-1.0.0.dist-info/RECORD
