Metadata-Version: 2.4
Name: dj-apis-allauth
Version: 1.0.0
Summary: Secure API Endpoints Authentication with Django REST Framework
License: MIT
License-File: LICENSE
Keywords: pypi,poetry,packaging
Author: Prince Clumson-Eklu
Author-email: ameto888@protonmail.com
Requires-Python: >=3.12
Classifier: Development Status :: 5 - Production/Stable
Classifier: Intended Audience :: Developers
Classifier: Framework :: Django :: 5.2
Classifier: License :: OSI Approved :: MIT License
Classifier: Programming Language :: Python :: 3
Classifier: Programming Language :: Python :: 3.8
Classifier: Programming Language :: Python :: 3.9
Classifier: Programming Language :: Python :: 3.10
Classifier: Programming Language :: Python :: 3.11
Classifier: Programming Language :: Python :: 3.12
Classifier: Operating System :: OS Independent
Requires-Dist: django-allauth (>=65.11.2,<66.0.0)
Requires-Dist: djangorestframework-simplejwt (>=5.5.1,<6.0.0)
Requires-Dist: drf-spectacular (>=0.28.0,<0.29.0)
Requires-Dist: requests (>=2.32.5,<3.0.0)
